pytest_pogo/__init__.py
pytest_pogo-0.2.1.dist-info/METADATA
pytest_pogo-0.2.1.dist-info/WHEEL
pytest_pogo-0.2.1.dist-info/entry_points.txt
pytest_pogo-0.2.1.dist-info/RECORD
